{
    "version": "17", 
    "personal": {
        "submitter_name": "Yi-Qiang Cheng", 
        "submitter_institution": "University of North Texas Health Science Center", 
        "submitter_email": "yiqiang.cheng@unthsc.edu"
    }, 
    "general_params": {
        "mibig_accession": "BGC0000993", 
        "biosyn_class": [
            "NRP", 
            "Polyketide"
        ], 
        "publications": "17400765, 19549597, 21183645, 21183648, 24553401", 
        "loci": {
            "complete": "complete", 
            "nucl_acc": [
                {
                    "Accession": "EF210776", 
                    "start_coord": 2513, 
                    "end_coord": 39006, 
                    "conn_comp_cluster": [
                        "Knock-out studies", 
                        "Enzymatic assays", 
                        "Heterologous expression", 
                        "Sequence-based prediction"
                    ]
                }
            ]
        }, 
        "compounds": [
            {
                "compound": "FK228", 
                "chem_synonyms": [
                    "depsipeptide", 
                    "romidepsin"
                ], 
                "chem_struct": "CC=C1C(=O)NC(C(=O)OC2CC(=O)NC(C(=O)NC(CSSCCC=C2)C(=O)N1)C(C)C)C(C)C", 
                "molecular_formula": "C24H36N4O6S2", 
                "mol_mass": 540.2, 
                "mass_ion_type": "None", 
                "chem_act": [
                    "Antifungal", 
                    "Cytotoxic", 
                    "Inhibitor"
                ], 
                "chem_target": "Histone deacetylases", 
                "chem_moieties": [
                    {
                        "chem_moiety": "Other", 
                        "other_chem_moiety": "Disulfide bond", 
                        "moiety_subcluster": [
                            "abp57753"
                        ]
                    }
                ]
            }
        ], 
        "genes": {
            "operon": [
                {
                    "operon_genes": [
                        "abp57745", 
                        "abp57746", 
                        "abp57747", 
                        "abp57748", 
                        "abp57749", 
                        "abp57750", 
                        "abp57751", 
                        "abp57752", 
                        "abp57753", 
                        "abp57754"
                    ], 
                    "evidence_operon": "Other"
                }
            ]
        }, 
        "NRP": {
            "subclass": "Cyclic depsipeptide", 
            "lin_cycl_nrp": "Cyclic", 
            "nrps_te_type": "Type II", 
            "nrps_release_type": "Macrolactamization"
        }, 
        "Polyketide": {
            "pk_subclass": "Macrolide", 
            "lin_cycl_pk": "Cyclic", 
            "pks_subclass": [
                "Modular type I"
            ], 
            "starter_unit": "Malonyl-CoA", 
            "pks_te_type": "Type II", 
            "pks_thioesterase": [
                "abp57754"
            ], 
            "pks_release_type": "Macrolactamization"
        }
    }
}

